cpboredbutton/__init__.py
cpboredbutton/cf_recommend.py
cpboredbutton-1.0.data/scripts/cpboredbutton
cpboredbutton-1.0.dist-info/LICENSE
cpboredbutton-1.0.dist-info/METADATA
cpboredbutton-1.0.dist-info/WHEEL
cpboredbutton-1.0.dist-info/top_level.txt
cpboredbutton-1.0.dist-info/RECORD
