Metadata-Version: 2.1
Name: cpboredbutton
Version: 1.0
Summary: Competitive programming problem recommendation
Home-page: https://github.com/vishalananth07/CP-Bored-Button
Author: vishalananth, anishbadri
Author-email: vishalananth98@gmail.com, anishbadhri@gmail.com
License: UNKNOWN
Platform: UNKNOWN
Classifier: Programming Language :: Python :: 3
Classifier: License :: OSI Approved :: MIT License
Classifier: Operating System :: OS Independent
Requires-Python: >=3
